aicommitter/__init__.py
aicommitter/generate_message.py
aicommitter/resources/__init__.py
aicommitter/resources/docs.md
aicommitter-1.0.6.dist-info/licenses/LICENSE
aicommitter-1.0.6.dist-info/METADATA
aicommitter-1.0.6.dist-info/WHEEL
aicommitter-1.0.6.dist-info/entry_points.txt
aicommitter-1.0.6.dist-info/top_level.txt
aicommitter-1.0.6.dist-info/RECORD
