Metadata-Version: 2.4
Name: aicommitter
Version: 1.0.6
Summary: AI powered commit message helper
Author: ifaakash
License: MIT
Keywords: git,commit,ai,devops,cli,commit message
Requires-Python: >=3.7.9
License-File: LICENSE
Requires-Dist: typer[all]>=0.9.0
Requires-Dist: requests>=2.28
Requires-Dist: python-dotenv>=1.0
Dynamic: license-file
